hello_tls/__init__.py
hello_tls/__main__.py
hello_tls/names_and_numbers.py
hello_tls/protocol.py
hello_tls/scan.py
hello_tls-0.4.0.dist-info/LICENSE
hello_tls-0.4.0.dist-info/METADATA
hello_tls-0.4.0.dist-info/WHEEL
hello_tls-0.4.0.dist-info/top_level.txt
hello_tls-0.4.0.dist-info/RECORD
