Metadata-Version: 2.1
Name: hello_tls
Version: 0.4.0
Summary: Create TLS Client Hello messages and scan server capabilities
Author-email: BoppreH <github@boppreh.com>
Project-URL: Homepage, https://github.com/boppreh/hello_tls
Project-URL: Bug Tracker, https://github.com/boppreh/hello_tls/issues
Classifier: Programming Language :: Python :: 3
Classifier: License :: OSI Approved :: MIT License
Classifier: Operating System :: OS Independent
Requires-Python: >=3.9
License-File: LICENSE
Requires-Dist: pyOpenSSL >=23.0.0
